src/Adder.v
module Adder(a, b ,c);
    
    input [31:0] a, b; 
    output [31:0] c; 

    assign c = a + b;

endmodule

code/imemory.v
module imemory(reset, A, RD);

    input reset;
    input[31:0] A;
    output[31:0] RD; 

    reg[31:0] mem [1023:0];

    assign RD = (reset == 1'b0) ? {32{1'b0}} : mem[A[31:2]]; 

    
  initial begin
    $readmemh("memfile.hex",mem);
  end     



endmodule

code/Program_counter.v
module Program_counter(clk, reset, counter, counter_next);

    input clk, reset;
    input[31:0] counter_next; 
    output [31:0] counter; 
    reg [31:0] counter;


    always @(posedge clk) begin
        if (reset == 1'b0)begin
            counter <= {32{1'b0}};
        end
        else begin 
            counter <= counter_next;
        end  
    end

endmodule

src/MUX.v
module mux (a,b,s,c);

    input[31:0] a, b; 
    input s; 
    output[31:0] c; 

    assign c = (~s) ? a : b;


endmodule

src/Fetch_cycle.v
`include "Program_counter.v"
`include "MUX.v"
`include "imemory.v"
`include "Adder.v" 
module fetch_cycle(clk, reset, PCsrcE, PCTargetE, InstrD, PCD, PCPlus4D);

    //inputs and outputs
    input clk, reset;
    input PCsrcE;
    input [31:0]PCTargetE; 
    output [31:0]InstrD, PCD, PCPlus4D;
    //wire 
    wire [31:0] PC_F, PCF, PCPLUS4F;
    wire[31:0] InstrF; 

    reg[31:0] InstrF_reg;
    reg[31:0] PCF_reg, PCPLUS4F_reg;


    //mux
    mux PC_Mux (.a(PCPLUS4F),.b(PCTargetE),.s(PCsrcE),.c(PC_F));
    // program counter
    Program_counter PC(.clk(clk), .reset(reset), .counter(PCF), .counter_next(PC_F));

    // IMemory
    imemory imem(.reset(reset), .A(PCF), .RD(InstrF));

    // Program counter adder 
    Adder PC_adder(.a(PCF), .b(32'h00000004), .c(PCPLUS4F));


    always @(posedge clk or negedge reset) begin
        if (reset == 1'b0) begin
            InstrF_reg <= 32'h00000000;
            PCF_reg <= 32'h00000000;
            PCPLUS4F_reg <= 32'h00000000;
        end
        else begin
            InstrF_reg <= InstrF; 
            PCF_reg <= PCF;
            PCPLUS4F_reg <= PCPLUS4F;
        end

    end

    assign InstrD = (reset == 1'b0) ? 32'h00000000 : InstrF_reg;
    assign PCD = (reset == 1'b0) ? 32'h00000000 : PCF_reg; 
    assign PCPlus4D = (reset == 1'b0) ? 32'h00000000 : PCPLUS4F_reg;





endmodule

src/fetch_cycle_tb.v
module tb();

    reg clk, reset, PCsrcE; 
    reg [31:0] PCTargetE;
    wire [31:0] InstrD, PCD, PCPlus4D;

    //declare the DUT (design under test)
    fetch_cycle DUT(.clk(clk), .reset(reset), .PCsrcE(PCsrcE), .PCTargetE(PCTargetE), .InstrD(InstrD), .PCD(PCD), .PCPlus4D(PCPlus4D));

    initial clk = 0;
    always #50 clk = ~clk; 

    initial begin
        reset <= 1'b0; 
        #200; 
        reset <= 1'b1; 
        PCsrcE <= 1'b0; 
        PCTargetE <= 32'h00000000;
        #500;
        $finish;
    end

    initial begin 
        $dumpfile("dump.vcd");
        $dumpvars(0);
    end

endmodule

src/dump.vcd
$date
	Sun Oct  5 20:32:32 2025
$end
$version
	Icarus Verilog
$end
$timescale
	1s
$end
$scope module tb $end
$var wire 32 ! PCPlus4D [31:0] $end
$var wire 32 " PCD [31:0] $end
$var wire 32 # InstrD [31:0] $end
$var reg 32 $ PCTargetE [31:0] $end
$var reg 1 % PCsrcE $end
$var reg 1 & clk $end
$var reg 1 ' reset $end
$scope module DUT $end
$var wire 32 ( PCTargetE [31:0] $end
$var wire 1 % PCsrcE $end
$var wire 1 & clk $end
$var wire 1 ' reset $end
$var wire 32 ) PC_F [31:0] $end
$var wire 32 * PCPlus4D [31:0] $end
$var wire 32 + PCPLUS4F [31:0] $end
$var wire 32 , PCF [31:0] $end
$var wire 32 - PCD [31:0] $end
$var wire 32 . InstrF [31:0] $end
$var wire 32 / InstrD [31:0] $end
$var reg 32 0 InstrF_reg [31:0] $end
$var reg 32 1 PCF_reg [31:0] $end
$var reg 32 2 PCPLUS4F_reg [31:0] $end
$scope module PC $end
$var wire 1 & clk $end
$var wire 1 ' reset $end
$var wire 32 3 counter_next [31:0] $end
$var reg 32 4 counter [31:0] $end
$upscope $end
$scope module PC_Mux $end
$var wire 32 5 b [31:0] $end
$var wire 1 % s $end
$var wire 32 6 c [31:0] $end
$var wire 32 7 a [31:0] $end
$upscope $end
$scope module PC_adder $end
$var wire 32 8 a [31:0] $end
$var wire 32 9 b [31:0] $end
$var wire 32 : c [31:0] $end
$upscope $end
$scope module imem $end
$var wire 32 ; A [31:0] $end
$var wire 1 ' reset $end
$var wire 32 < RD [31:0] $end
$upscope $end
$upscope $end
$upscope $end
$enddefinitions $end
#0
$dumpvars
b0 <
bx ;
bx :
b100 9
bx 8
bx 7
bx 6
bx 5
bx 4
bx 3
b0 2
b0 1
b0 0
b0 /
b0 .
b0 -
bx ,
bx +
b0 *
bx )
bx (
0'
0&
x%
bx $
b0 #
b0 "
b0 !
$end
#50
b100 +
b100 7
b100 :
b0 ,
b0 4
b0 8
b0 ;
1&
#100
0&
#150
1&
#200
b10100000000001010010011 .
b10100000000001010010011 <
b100 )
b100 3
b100 6
b0 $
b0 (
b0 5
0%
1'
0&
#250
b1100000000001100010011 .
b1100000000001100010011 <
b1000 )
b1000 3
b1000 6
b100 !
b100 *
b10100000000001010010011 #
b10100000000001010010011 /
b1000 +
b1000 7
b1000 :
b100 ,
b100 4
b100 8
b100 ;
b100 2
b10100000000001010010011 0
1&
#300
0&
#350
b11000101000001110110011 .
b11000101000001110110011 <
b1100 )
b1100 3
b1100 6
b1000 !
b1000 *
b100 "
b100 -
b1100000000001100010011 #
b1100000000001100010011 /
b1100 +
b1100 7
b1100 :
b1000 ,
b1000 4
b1000 8
b1000 ;
b1000 2
b100 1
b1100000000001100010011 0
1&
#400
0&
#450
b10010000000011 .
b10010000000011 <
b10000 )
b10000 3
b10000 6
b1100 !
b1100 *
b1000 "
b1000 -
b11000101000001110110011 #
b11000101000001110110011 /
b10000 +
b10000 7
b10000 :
b1100 ,
b1100 4
b1100 8
b1100 ;
b1100 2
b1000 1
b11000101000001110110011 0
1&
#500
0&
#550
b100000000010010010011 .
b100000000010010010011 <
b10100 )
b10100 3
b10100 6
b10000 !
b10000 *
b1100 "
b1100 -
b10010000000011 #
b10010000000011 /
b10100 +
b10100 7
b10100 :
b10000 ,
b10000 4
b10000 8
b10000 ;
b10000 2
b1100 1
b10010000000011 0
1&
#600
0&
#650
b100101000000010100110011 .
b100101000000010100110011 <
b11000 )
b11000 3
b11000 6
b10100 !
b10100 *
b10000 "
b10000 -
b100000000010010010011 #
b100000000010010010011 /
b11000 +
b11000 7
b11000 :
b10100 ,
b10100 4
b10100 8
b10100 ;
b10100 2
b10000 1
b100000000010010010011 0
1&
